setup.py
bigbox/__init__.py
bigbox/__main__.py
bigbox/big_box_model.py
bigbox/big_box_run.py
indra/__init__.py
indra/__main__.py
indra/agent_pop.py
indra/api.py
indra/data_methods.py
indra/display_methods.py
indra/entity.py
indra/entry_point.py
indra/env.py
indra/grid_agent.py
indra/grid_env.py
indra/main_menu.py
indra/markov.py
indra/markov_agent.py
indra/markov_env.py
indra/menu.py
indra/node.py
indra/prehension.py
indra/prehension_agent.py
indra/prop_args.py
indra/spatial_agent.py
indra/spatial_env.py
indra/two_pop_markov.py
indra/two_pop_model.py
indra/user.py
indra/utils.py
indra/vector_space.py
indra/vs_agent.py
indras_net.egg-info/PKG-INFO
indras_net.egg-info/SOURCES.txt
indras_net.egg-info/dependency_links.txt
indras_net.egg-info/entry_points.txt
indras_net.egg-info/not-zip-safe
indras_net.egg-info/requires.txt
indras_net.egg-info/top_level.txt
models/__init__.py
models/__main__.py
models/basic_model.py
models/basic_run.py
models/coop_model.py
models/coop_run.py
models/fashion_model.py
models/fashion_run.py
models/fmarket_model.py
models/fmarket_run.py
models/forestfire_model.py
models/forestfire_run.py
models/grid_model.py
models/grid_run.py
models/menu_model.py
models/menu_run.py
models/obst_model.py
models/obst_run.py
models/plane_model.py
models/sand_model.py
models/sand_run.py
models/spatial_model.py
models/spatial_run.py
models/two_pop_model.py
models/two_pop_run.py
models/wolfsheep_model.py
models/wolfsheep_run.py
schelling/__init__.py
schelling/__main__.py
schelling/auditorium_model.py
schelling/auditorium_run.py
schelling/height_model.py
schelling/height_run.py
schelling/segregation_model.py
schelling/segregation_run.py